LICENSE
README.md
setup.py
Data/__init__.py
countyPackage.egg-info/PKG-INFO
countyPackage.egg-info/SOURCES.txt
countyPackage.egg-info/dependency_links.txt
countyPackage.egg-info/requires.txt
countyPackage.egg-info/top_level.txt
county_package/EDA.py
county_package/__init__.py
county_package/clean_data.py
county_package/prediction.py